<?xml version="1.0" encoding="utf-8"?>
<message_catalog package_key="bulk-mail" locale="pl_PL" charset="utf-8">

  <msg key="Cancelled">Anulowano</msg>
  <msg key="Extra_Headers">Dodatkowe Nagłówki</msg>
  <msg key="From">Od</msg>
  <msg key="lt_No_bulk_mail_messages">Brak komunikatów do wyświetlenia.</msg>
  <msg key="Message">Komunikat</msg>
  <msg key="Message_not_sent_yet">Nie wysłano jeszcze tego komunikatu. Możesz go &lt;a href=&quot;cancel?bulk_mail_id=%bulk_mail_id%&quot;&gt; anulowaćl&lt;/a&gt;.</msg>
  <msg key="No">Nie</msg>
  <msg key="Pending">Oczekujący</msg>
  <msg key="pretty_name">Poczta Hurtowa</msg>
  <msg key="Query">Pytanie</msg>
  <msg key="Reply_To">Odpowiedz</msg>
  <msg key="Send_Date">Data Wysłania</msg>
  <msg key="Sent">Wysłać?</msg>
  <msg key="Status">Status</msg>
  <msg key="Subject">Temat</msg>
  <msg key="Yes">Tak</msg>
</message_catalog>
